ez_appinstaller/__init__.py
ez_appinstaller/cli.py
EZ_AppInstaller-1.0.dist-info/LICENSE
EZ_AppInstaller-1.0.dist-info/METADATA
EZ_AppInstaller-1.0.dist-info/WHEEL
EZ_AppInstaller-1.0.dist-info/entry_points.txt
EZ_AppInstaller-1.0.dist-info/top_level.txt
EZ_AppInstaller-1.0.dist-info/RECORD
