Metadata-Version: 2.1
Name: EZ-AppInstaller
Version: 1.0
Summary: A cli tool to easily install applications that don't have an installer.
Home-page: https://github.com/bananapizzuh/ez-appinstaller
Author: bananapizzuh
License: MIT
Platform: win32
Platform: win64
License-File: LICENSE
Requires-Dist: rich-click
Requires-Dist: pyyaml
Requires-Dist: pywin32
